aiomqtt_router-0.1.0.dist-info/METADATA
aiomqtt_router-0.1.0.dist-info/WHEEL
aiomqtt_router/__init__.py
aiomqtt_router-0.1.0.dist-info/RECORD
