Metadata-Version: 2.1
Name: aiomqtt-router
Version: 0.1.0
Summary: Graceful routing of aiomqtt subscriptions
Author-Email: Matthew Badger <matt@branchenergy.com>
License: MIT
Requires-Python: >=3.11
Requires-Dist: aiomqtt>=2.1.0
